{"cameraMode":{"drawMode":0,"name":"Shaded","section":"Shading Mode"},"sceneLighting":false,"audioPlay":false,"sceneViewState":{"m_AlwaysRefresh":false,"showFog":true,"showSkybox":false,"showFlares":true,"showImageEffects":true,"showParticleSystems":true,"showVisualEffectGraphs":true,"m_FxEnabled":true},"in2DMode":false,"pivot":{"x":5.960464477539063e-8,"y":0.0,"z":-1.1920928955078126e-7},"rotation":{"x":0.23216187953948975,"y":-0.009913597255945206,"z":0.002356685232371092,"w":0.972628116607666},"size":2.1247448921203615,"orthographic":false}